setup.py
distributions_final/Binomialdistribution.py
distributions_final/Gaussiandistribution.py
distributions_final/Generaldistribution.py
distributions_final/__init__.py
distributions_final.egg-info/PKG-INFO
distributions_final.egg-info/SOURCES.txt
distributions_final.egg-info/dependency_links.txt
distributions_final.egg-info/not-zip-safe
distributions_final.egg-info/top_level.txt